pybalance/__init__.py
pybalance/genetic/__init__.py
pybalance/genetic/initialization.py
pybalance/genetic/logger.py
pybalance/genetic/matcher.py
pybalance/genetic/tests/__init__.py
pybalance/genetic/tests/test_genetic.py
pybalance/lp/__init__.py
pybalance/lp/matcher.py
pybalance/lp/tests/__init__.py
pybalance/lp/tests/test_lp_matcher.py
pybalance/propensity/__init__.py
pybalance/propensity/matcher.py
pybalance/propensity/tests/__init__.py
pybalance/propensity/tests/test_propensity.py
pybalance/sim/__init__.py
pybalance/sim/rng.py
pybalance/sim/data/pool250000-target25000-normal0-lognormal0-binary4.parquet
pybalance/sim/tests/__init__.py
pybalance/sim/tests/test_datasets.py
pybalance/sim/tests/test_sim.py
pybalance/utils/__init__.py
pybalance/utils/balance_calculators.py
pybalance/utils/matching_data.py
pybalance/utils/misc.py
pybalance/utils/preprocess.py
pybalance/utils/tests/__init__.py
pybalance/utils/tests/test_balance_calculators.py
pybalance/utils/tests/test_matching_data.py
pybalance/utils/tests/test_preprocess.py
pybalance/visualization/__init__.py
pybalance/visualization/distributions.py
pybalance/visualization/history.py
pybalance/visualization/tests/__init__.py
pybalance/visualization/tests/test_visualization.py
pybalance-0.2.3.dist-info/LICENSE
pybalance-0.2.3.dist-info/METADATA
pybalance-0.2.3.dist-info/WHEEL
pybalance-0.2.3.dist-info/top_level.txt
pybalance-0.2.3.dist-info/RECORD
