Metadata-Version: 2.1
Name: pybalance
Version: 0.2.3
Summary: Population Matching
Home-page: UNKNOWN
Author: Stephen Privitera
Author-email: stephen.privitera@bayer.com
License: UNKNOWN
Platform: UNKNOWN
Classifier: Programming Language :: Python :: 3
Classifier: License :: OSI Approved :: BSD License
Classifier: Operating System :: OS Independent
Requires-Python: >=3.9
License-File: LICENSE
Requires-Dist: setuptools
Requires-Dist: PyYAML
Requires-Dist: matplotlib
Requires-Dist: numpy<2
Requires-Dist: pandas
Requires-Dist: pyarrow
Requires-Dist: pytest
Requires-Dist: scikit-learn
Requires-Dist: scipy
Requires-Dist: seaborn
Requires-Dist: ortools==9.9.3963
Requires-Dist: torch>=2.0.0
